odoo/addons/product_customerinfo/README.rst
odoo/addons/product_customerinfo/__init__.py
odoo/addons/product_customerinfo/__manifest__.py
odoo/addons/product_customerinfo/demo/product_demo.xml
odoo/addons/product_customerinfo/i18n/ca.po
odoo/addons/product_customerinfo/i18n/de.po
odoo/addons/product_customerinfo/i18n/es.po
odoo/addons/product_customerinfo/i18n/fr.po
odoo/addons/product_customerinfo/i18n/it.po
odoo/addons/product_customerinfo/i18n/nl.po
odoo/addons/product_customerinfo/i18n/nl_NL.po
odoo/addons/product_customerinfo/i18n/product_customerinfo.pot
odoo/addons/product_customerinfo/i18n/product_supplierinfo_for_customer.pot
odoo/addons/product_customerinfo/i18n/pt_BR.po
odoo/addons/product_customerinfo/i18n/sl.po
odoo/addons/product_customerinfo/i18n/tr.po
odoo/addons/product_customerinfo/models/__init__.py
odoo/addons/product_customerinfo/models/product_customerinfo.py
odoo/addons/product_customerinfo/models/product_pricelist.py
odoo/addons/product_customerinfo/models/product_product.py
odoo/addons/product_customerinfo/models/product_supplierinfo.py
odoo/addons/product_customerinfo/models/product_template.py
odoo/addons/product_customerinfo/models/res_partner.py
odoo/addons/product_customerinfo/readme/CONFIGURE.md
odoo/addons/product_customerinfo/readme/CONTRIBUTORS.md
odoo/addons/product_customerinfo/readme/DESCRIPTION.md
odoo/addons/product_customerinfo/readme/ROADMAP.md
odoo/addons/product_customerinfo/readme/USAGE.md
odoo/addons/product_customerinfo/security/ir.model.access.csv
odoo/addons/product_customerinfo/static/description/icon.png
odoo/addons/product_customerinfo/static/description/index.html
odoo/addons/product_customerinfo/static/xls/product_customerinfo.xls
odoo/addons/product_customerinfo/tests/__init__.py
odoo/addons/product_customerinfo/tests/test_product_customerinfo.py
odoo/addons/product_customerinfo/tests/test_product_name_search.py
odoo/addons/product_customerinfo/views/product_views.xml
odoo_addon_product_customerinfo-18.0.1.2.0.4.dist-info/METADATA
odoo_addon_product_customerinfo-18.0.1.2.0.4.dist-info/WHEEL
odoo_addon_product_customerinfo-18.0.1.2.0.4.dist-info/top_level.txt
odoo_addon_product_customerinfo-18.0.1.2.0.4.dist-info/RECORD
